mssqldbfade/__init__.py
mssqldbfade/facade.py
mssqldbfade/singleton.py
mssqldbfade-0.0.7.dist-info/LICENSE
mssqldbfade-0.0.7.dist-info/METADATA
mssqldbfade-0.0.7.dist-info/WHEEL
mssqldbfade-0.0.7.dist-info/top_level.txt
mssqldbfade-0.0.7.dist-info/RECORD
